AUTHORS
CHANGELOG.txt
DESCRIPTION
LICENSE
MANIFEST.in
README.rst
setup.py
django_forms_ajaxified.egg-info/PKG-INFO
django_forms_ajaxified.egg-info/SOURCES.txt
django_forms_ajaxified.egg-info/dependency_links.txt
django_forms_ajaxified.egg-info/requires.txt
django_forms_ajaxified.egg-info/top_level.txt
forms_ajaxified/__init__.py
forms_ajaxified/admin.py
forms_ajaxified/models.py
forms_ajaxified/urls.py
forms_ajaxified/views.py
forms_ajaxified/static/.empty
forms_ajaxified/static/forms_ajaxified/.empty
forms_ajaxified/static/forms_ajaxified/js/forms_ajaxified.js
forms_ajaxified/templates/forms_ajaxified/.empty
forms_ajaxified/templatetags/__init__.py
forms_ajaxified/templatetags/forms_ajaxified_tags.py
forms_ajaxified/tests/__init__.py
forms_ajaxified/tests/forms_ajaxified_tags_tests.py
forms_ajaxified/tests/settings.py
forms_ajaxified/tests/test_settings.py
forms_ajaxified/tests/urls.py
forms_ajaxified/tests/views_tests.py
forms_ajaxified/tests/test_app/__init__.py
forms_ajaxified/tests/test_app/forms.py
forms_ajaxified/tests/test_app/models.py
forms_ajaxified/tests/test_app/urls.py
forms_ajaxified/tests/test_app/views.py
forms_ajaxified/tests/test_app/static/js/libs/jquery-1.11.1.js
forms_ajaxified/tests/test_app/templates/400.html
forms_ajaxified/tests/test_app/templates/500.html
forms_ajaxified/tests/test_app/templates/base.html
forms_ajaxified/tests/test_app/templates/test_app/dummy_template.html
forms_ajaxified/tests/test_app/templates/test_app/partials/dummy_form.html
forms_ajaxified/tests/test_app/templates/test_app/partials/dummy_form_wrapper.html