Metadata-Version: 1.0
Name: django-forms-ajaxified
Version: 0.2
Summary: A reusable Django app that allows to load and submit forms via AJAX.
